[
  {
    "title": "Data Analyst",
    "company": "PinnacleU",
    "location": "Gurugram, Haryana",
    "salary": "",
    "posted_date": "",
    "description": "Data Analyst",
    "search_term": "Data Analyst",
    "search_location": "India",
    "scraped_at": "2026-03-23T10:41:34.318045"
  },
  {
    "title": "Data Analyst",
    "company": "Matrix Global",
    "location": "Remote",
    "salary": "",
    "posted_date": "",
    "description": "Data Analyst",
    "search_term": "Data Analyst",
    "search_location": "India",
    "scraped_at": "2026-03-23T10:41:35.051636"
  },
  {
    "title": "Data Analyst",
    "company": "Madison Logic",
    "location": "Remote in Pune, Maharashtra",
    "salary": "",
    "posted_date": "",
    "description": "Data Analyst",
    "search_term": "Data Analyst",
    "search_location": "India",
    "scraped_at": "2026-03-23T10:41:35.712938"
  },
  {
    "title": "Data Analyst - SQL",
    "company": "YO IT CONSULTING",
    "location": "Remote in India",
    "salary": "",
    "posted_date": "",
    "description": "Data Analyst - SQL",
    "search_term": "Data Analyst",
    "search_location": "India",
    "scraped_at": "2026-03-23T10:41:36.384653"
  },
  {
    "title": "Data Analyst",
    "company": "DigitalXC",
    "location": "Remote",
    "salary": "",
    "posted_date": "",
    "description": "Data Analyst",
    "search_term": "Data Analyst",
    "search_location": "India",
    "scraped_at": "2026-03-23T10:41:37.335477"
  },
  {
    "title": "Data Analyst",
    "company": "Airbus India Private Limited",
    "location": "Bengaluru, Karnataka",
    "salary": "",
    "posted_date": "",
    "description": "Data Analyst",
    "search_term": "Data Analyst",
    "search_location": "India",
    "scraped_at": "2026-03-23T10:41:38.254927"
  },
  {
    "title": "Upstream Data Analyst",
    "company": "Quest Global",
    "location": "Bengaluru, Karnataka",
    "salary": "",
    "posted_date": "",
    "description": "Upstream Data Analyst",
    "search_term": "Data Analyst",
    "search_location": "India",
    "scraped_at": "2026-03-23T10:41:38.855006"
  },
  {
    "title": "Jr Data Analyst",
    "company": "Veracity Software",
    "location": "Remote in India",
    "salary": "",
    "posted_date": "",
    "description": "Jr Data Analyst",
    "search_term": "Data Analyst",
    "search_location": "India",
    "scraped_at": "2026-03-23T10:41:39.857125"
  },
  {
    "title": "Data Analyst",
    "company": "Kidvento Education and Research",
    "location": "Bengaluru, Karnataka",
    "salary": "",
    "posted_date": "",
    "description": "Data Analyst",
    "search_term": "Data Analyst",
    "search_location": "India",
    "scraped_at": "2026-03-23T10:41:40.831866"
  },
  {
    "title": "Data Analyst",
    "company": "Discover Dollar",
    "location": "Bengaluru, Karnataka",
    "salary": "",
    "posted_date": "",
    "description": "Data Analyst",
    "search_term": "Data Analyst",
    "search_location": "India",
    "scraped_at": "2026-03-23T10:41:41.634521"
  },
  {
    "title": "Data Analyst II",
    "company": "Better Mortgage",
    "location": "Remote in India",
    "salary": "",
    "posted_date": "",
    "description": "Data Analyst II",
    "search_term": "Data Analyst",
    "search_location": "India",
    "scraped_at": "2026-03-23T10:41:42.458303"
  },
  {
    "title": "Data Analyst",
    "company": "Barclays",
    "location": "Pune, Maharashtra",
    "salary": "",
    "posted_date": "",
    "description": "Data Analyst",
    "search_term": "Data Analyst",
    "search_location": "India",
    "scraped_at": "2026-03-23T10:41:43.335441"
  },
  {
    "title": "Data Visualization Analyst (India)",
    "company": "Applied Systems, Inc.",
    "location": "Bengaluru, Karnataka",
    "salary": "",
    "posted_date": "",
    "description": "Data Visualization Analyst (India)",
    "search_term": "Data Analyst",
    "search_location": "India",
    "scraped_at": "2026-03-23T10:41:45.110081"
  },
  {
    "title": "Data Analyst",
    "company": "Scry Analytics India Pvt Ltd",
    "location": "Belgaum, Karnataka",
    "salary": "",
    "posted_date": "",
    "description": "Data Analyst",
    "search_term": "Data Analyst",
    "search_location": "India",
    "scraped_at": "2026-03-23T10:41:45.951771"
  },
  {
    "title": "Data Analyst",
    "company": "Keywords Studios",
    "location": "Hybrid work in Pune, Maharashtra",
    "salary": "",
    "posted_date": "",
    "description": "Data Analyst",
    "search_term": "Data Analyst",
    "search_location": "India",
    "scraped_at": "2026-03-23T10:41:46.597793"
  }
]